aws_lambda_pypackager-0.1.0.dist-info/METADATA
aws_lambda_pypackager-0.1.0.dist-info/RECORD
aws_lambda_pypackager-0.1.0.dist-info/WHEEL
aws_lambda_pypackager-0.1.0.dist-info/entry_points.txt
aws_lambda_pypackager-0.1.0.dist-info/top_level.txt
pypackager/__init__.py
pypackager/shell.py
