Metadata-Version: 2.1
Name: aws-lambda-pypackager
Version: 0.1.0
Summary: Opinionated packaging helper for Python AWS Lambda Projects.
Home-page: https://github.com/jarosser06/aws-lambda-pypackager
Author: Jim Rosser
Maintainer-email: jarosser06@gmail.com
License: MIT
Keywords: aws lambda serverless
Platform: UNKNOWN
Classifier: Programming Language :: Python :: 3
Classifier: Programming Language :: Python :: 3.6
Classifier: Programming Language :: Python :: 3.7
Classifier: License :: OSI Approved :: MIT License
Classifier: Operating System :: OS Independent
Provides-Extra: test
Provides-Extra: lint
Provides-Extra: style
Provides-Extra: test-requirements
Requires-Dist: boto3 (>=1.7.57)
Requires-Dist: lambda-uploader (>=1.3.0)
Requires-Dist: jinja2 (>=2.10)
Provides-Extra: lint
Requires-Dist: flake8 (>=3.5.0); extra == 'lint'
Requires-Dist: pylint (>=1.9.2); extra == 'lint'
Provides-Extra: style
Requires-Dist: flake8 (>=3.5.0); extra == 'style'
Requires-Dist: pylint (>=1.9.2); extra == 'style'
Provides-Extra: test
Provides-Extra: test-requirements
Requires-Dist: flake8 (>=3.5.0); extra == 'test-requirements'
Requires-Dist: pylint (>=1.9.2); extra == 'test-requirements'
